krypton/server/__init__.py
krypton/server/py.typed
krypton_server-0.1.0.dev5.dist-info/LICENSE
krypton_server-0.1.0.dev5.dist-info/METADATA
krypton_server-0.1.0.dev5.dist-info/WHEEL
krypton_server-0.1.0.dev5.dist-info/RECORD
